schemdraw_mcp_server/__init__.py
schemdraw_mcp_server/server.py
iflow_mcp_schemdraw_mcp_server-0.1.0.dist-info/METADATA
iflow_mcp_schemdraw_mcp_server-0.1.0.dist-info/WHEEL
iflow_mcp_schemdraw_mcp_server-0.1.0.dist-info/entry_points.txt
iflow_mcp_schemdraw_mcp_server-0.1.0.dist-info/RECORD
