Metadata-Version: 2.4
Name: iflow-mcp_schemdraw-mcp-server
Version: 0.1.0
Summary: MCP Server for schemdraw - Electronic circuit diagram drawing
Project-URL: Homepage, https://github.com/fukayatti/schemdraw-mcp-server
Project-URL: Repository, https://github.com/fukayatti/schemdraw-mcp-server
Project-URL: Issues, https://github.com/fukayatti/schemdraw-mcp-server/issues
Author-email: fukayatti0 <contact@fukayatti0.dev>
License: MIT
Keywords: circuit,diagram,electronics,mcp,schemdraw
Classifier: Development Status :: 3 - Alpha
Classifier: Intended Audience :: Developers
Classifier: License :: OSI Approved :: MIT License
Classifier: Programming Language :: Python :: 3
Classifier: Programming Language :: Python :: 3.9
Classifier: Programming Language :: Python :: 3.10
Classifier: Programming Language :: Python :: 3.11
Classifier: Programming Language :: Python :: 3.12
Requires-Python: >=3.10
Requires-Dist: matplotlib>=3.5.0
Requires-Dist: mcp>=1.0.0
Requires-Dist: numpy>=1.20.0
Requires-Dist: pillow>=8.0.0
Requires-Dist: schemdraw>=0.15
Provides-Extra: dev
Requires-Dist: black>=23.0.0; extra == 'dev'
Requires-Dist: flake8>=6.0.0; extra == 'dev'
Requires-Dist: isort>=5.12.0; extra == 'dev'
Requires-Dist: mypy>=1.0.0; extra == 'dev'
Requires-Dist: pytest-asyncio>=0.21.0; extra == 'dev'
Requires-Dist: pytest>=7.0.0; extra == 'dev'
